{"count":3,"results":[{"id":1,"oauth_id":null,"name":"admin","password":"$bcrypt-sha256$v=2,t=2b,r=12$0K/88LaydHqMEFdWpi4NZu$lo04EAUr/Y6ucBzJ5Y6DJ/jecuOFEc2","email":"green@redhat.com","type":"admin","secret":null,"website":null,"affiliation":null,"country":null,"bracket":null,"hidden":1,"banned":0,"verified":0,"team_id":null,"created":"2023-08-11T14:58:06.125746","language":null},{"id":2,"oauth_id":null,"name":"Anthony Green","password":"$bcrypt-sha256$v=2,t=2b,r=12$Lkcqu4bnjAVxeVrLMtZBve$FX9zc2svJFNAhPI2LxeSjeWfuPstum2","email":"anthony@atgreen.org","type":"user","secret":null,"website":null,"affiliation":null,"country":null,"bracket":null,"hidden":0,"banned":0,"verified":0,"team_id":null,"created":"2023-08-11T18:20:38.767217","language":null},{"id":3,"oauth_id":null,"name":"joe","password":"$bcrypt-sha256$v=2,t=2b,r=12$gvMkijORFbsyZYEbk55vLO$VHejy2gnH0Mii68kuKaIDwKitrV18bS","email":"joe@example.com","type":"user","secret":null,"website":null,"affiliation":null,"country":null,"bracket":null,"hidden":0,"banned":0,"verified":0,"team_id":null,"created":"2023-08-11T18:35:34.616715","language":null}],"meta":{}}